CHANGES.txt
LICENSE.txt
MANIFEST.in
PROJECT.txt
README.rst
setup.py
pyseleniumfox/__init__.py
pyseleniumfox/pythonformatters@seleniumhq.org.xpi
pyseleniumfox/selenium-ide.xpi
pyseleniumfox.egg-info/PKG-INFO
pyseleniumfox.egg-info/SOURCES.txt
pyseleniumfox.egg-info/dependency_links.txt
pyseleniumfox.egg-info/not-zip-safe
pyseleniumfox.egg-info/requires.txt
pyseleniumfox.egg-info/top_level.txt